powerfactorypy/__init__.py
powerfactorypy/base_interface.py
powerfactorypy/case_studies.py
powerfactorypy/dyn_sim_interface.py
powerfactorypy/engineering_helpers.py
powerfactorypy/exceptions.py
powerfactorypy/plot_interface.py
powerfactorypy-0.0.6.dist-info/METADATA
powerfactorypy-0.0.6.dist-info/WHEEL
powerfactorypy-0.0.6.dist-info/licenses/LICENSE
powerfactorypy-0.0.6.dist-info/RECORD
