Metadata-Version: 2.1
Name: powerfactorypy
Version: 0.0.6
Summary: PowerFactory wrapper
Project-URL: Homepage, https://github.com/pypa/sampleproject
Project-URL: Bug Tracker, https://github.com/pypa/sampleproject/issues
Author-email: Sciemon <simon.eberlein@gmx.de>
License: Copyright (c) 2018 The Python Packaging Authority
Classifier: License :: OSI Approved :: MIT License
Classifier: Operating System :: OS Independent
Classifier: Programming Language :: Python :: 3
Requires-Python: >=3.7
Requires-Dist: matplotlib>1
Requires-Dist: pandas>1
